LICENSE
README.md
setup.py
loratransmit/RNode.py
loratransmit/__init__.py
loratransmit/loratransmit.py
loratransmit.egg-info/PKG-INFO
loratransmit.egg-info/SOURCES.txt
loratransmit.egg-info/dependency_links.txt
loratransmit.egg-info/entry_points.txt
loratransmit.egg-info/requires.txt
loratransmit.egg-info/top_level.txt