Metadata-Version: 2.1
Name: loratransmit
Version: 0.3.2
Summary: LoRa packet transmitter for RNode hardware
Home-page: https://github.com/randogoth/loratransmit
Author: randogoth
Author-email: randogoth@posteo.org
Classifier: Programming Language :: Python :: 3
Classifier: License :: OSI Approved :: MIT License
Classifier: Operating System :: OS Independent
Requires-Python: >=3.6
License-File: LICENSE
